{"name":"Event sheet 2","events":[{"eventType":"variable","name":"animation","type":"number","initialValue":"0","comment":"","isStatic":false,"isConstant":false,"sid":925919253539846},{"eventType":"block","conditions":[{"id":"on-start-of-layout","objectClass":"System","sid":437464478038561}],"actions":[{"id":"flash","objectClass":"pressSpace","sid":255147062484028,"behaviorType":"Flash","parameters":{"on-time":"1","off-time":"0.5","duration":"Infinity"}},{"id":"set-enabled","objectClass":"player","sid":967960418560070,"behaviorType":"Platform","parameters":{"state":"disabled"}},{"id":"set-animation","objectClass":"player","sid":182679863533882,"parameters":{"animation":"\"chooseColor\"","from":"beginning"}}],"sid":847990868662557},{"eventType":"block","conditions":[{"id":"on-key-pressed","objectClass":"Keyboard","sid":349785239993801,"parameters":{"key":32}}],"actions":[{"id":"flash","objectClass":"pressSpace","sid":956864874120339,"behaviorType":"Flash","parameters":{"on-time":"0.1","off-time":"0.1","duration":"3"}},{"id":"wait","objectClass":"System","sid":519047419731772,"parameters":{"seconds":"1"}},{"id":"go-to-nextprevious-layout","objectClass":"System","sid":393158227694279,"parameters":{"which":"next"}}],"sid":578205975643030},{"eventType":"block","conditions":[{"id":"on-key-pressed","objectClass":"Keyboard","sid":581554289668750,"parameters":{"key":32}},{"id":"compare-animation-frame","objectClass":"player","sid":365418898664081,"parameters":{"comparison":0,"number":"0"}}],"actions":[{"id":"set-eventvar-value","objectClass":"System","sid":386948270947498,"parameters":{"variable":"animation","value":"0"}},{"id":"set-animation","objectClass":"player","sid":372145177743141,"parameters":{"animation":"\"yellow\"","from":"beginning"}}],"sid":767982167653318},{"eventType":"block","conditions":[{"id":"on-key-pressed","objectClass":"Keyboard","sid":418232773878429,"parameters":{"key":32}},{"id":"compare-animation-frame","objectClass":"player","sid":322612055697004,"parameters":{"comparison":0,"number":"1"}}],"actions":[{"id":"set-eventvar-value","objectClass":"System","sid":995219128921724,"parameters":{"variable":"animation","value":"1"}},{"id":"set-animation","objectClass":"player","sid":380540119931169,"parameters":{"animation":"\"blue\"","from":"beginning"}}],"sid":301167406708960},{"eventType":"block","conditions":[{"id":"on-key-pressed","objectClass":"Keyboard","sid":839115733293038,"parameters":{"key":32}},{"id":"compare-animation-frame","objectClass":"player","sid":270366632614002,"parameters":{"comparison":0,"number":"2"}}],"actions":[{"id":"set-eventvar-value","objectClass":"System","sid":800833396691199,"parameters":{"variable":"animation","value":"2"}},{"id":"set-animation","objectClass":"player","sid":305133188673178,"parameters":{"animation":"\"LightPurple\"","from":"beginning"}}],"sid":682267904936199},{"eventType":"block","conditions":[{"id":"on-key-pressed","objectClass":"Keyboard","sid":879931733190493,"parameters":{"key":32}},{"id":"compare-animation-frame","objectClass":"player","sid":186061702643591,"parameters":{"comparison":0,"number":"3"}}],"actions":[{"id":"set-eventvar-value","objectClass":"System","sid":388480475807548,"parameters":{"variable":"animation","value":"3"}},{"id":"set-animation","objectClass":"player","sid":163911839173626,"parameters":{"animation":"\"Purple\"","from":"beginning"}}],"sid":238493091470449},{"eventType":"block","conditions":[{"id":"on-key-pressed","objectClass":"Keyboard","sid":819017828598606,"parameters":{"key":39}}],"actions":[{"id":"set-animation-frame","objectClass":"player","sid":225254370525213,"parameters":{"frame-number":"player.AnimationFrame+1"}},{"id":"set-active","objectClass":"arrows","sid":641958426817042,"behaviorType":"Sine","parameters":{"state":"active"}}],"sid":200727657291783,"isOrBlock":true},{"eventType":"block","conditions":[{"id":"on-key-pressed","objectClass":"Keyboard","sid":690609999038204,"parameters":{"key":37}}],"actions":[{"id":"set-animation-frame","objectClass":"player","sid":121257654038975,"parameters":{"frame-number":"player.AnimationFrame-1"}}],"sid":750102131783631,"isOrBlock":true}],"sid":490303223963713}